table_data_extractor/__init__.py
table_data_extractor/table_info_extractor.py
table_info_extractor-0.1.2.dist-info/LICENSE.txt
table_info_extractor-0.1.2.dist-info/METADATA
table_info_extractor-0.1.2.dist-info/WHEEL
table_info_extractor-0.1.2.dist-info/top_level.txt
table_info_extractor-0.1.2.dist-info/RECORD
