Metadata-Version: 2.1
Name: table-info-extractor
Version: 0.1.2
Summary: A package for extracting tables from images and PDFs
Home-page: https://github.com/raselmeya94/table_info_extractor
Author: Rasel Meya
Author-email: rhrasel94@gmail.com
Classifier: Programming Language :: Python :: 3
Classifier: License :: OSI Approved :: MIT License
Classifier: Operating System :: OS Independent
Requires-Python: >=3.6
License-File: LICENSE.txt
Requires-Dist: pdf2image
Requires-Dist: img2table
Requires-Dist: pytesseract
Requires-Dist: Pillow
Requires-Dist: ipython
Requires-Dist: pandas
Requires-Dist: opencv-python-headless
